skope/__init__.py
skope_py-0.1.3.dist-info/METADATA
skope_py-0.1.3.dist-info/WHEEL
skope_py-0.1.3.dist-info/top_level.txt
skope_py-0.1.3.dist-info/RECORD
